kvault/__init__.py
kvault/__main__.py
kvault/commands/__init__.py
kvault/exceptions.py
kvault/infra/__init__.py
kvault/infra/logger.py
kvault/protocol_handler.py
kvault/queue_server.py
kvault/socket_pool.py
kvault/threaded_stream_server.py
kvault/types.py
kvault/utils/__init__.py
kvault/utils/mixins.py
kvault-0.1.0.dist-info/LICENSE
kvault-0.1.0.dist-info/METADATA
kvault-0.1.0.dist-info/WHEEL
kvault-0.1.0.dist-info/RECORD
