Metadata-Version: 2.1
Name: kvault
Version: 0.1.0
Summary: Simple Miniature key-value datastore
License: MIT
Keywords: kvault,key-value-datastore,key-value
Author: BrianLusina
Author-email: 12752833+BrianLusina@users.noreply.github.com
Requires-Python: >=3.10,<4.0
Classifier: License :: OSI Approved :: MIT License
Classifier: Programming Language :: Python
Classifier: Programming Language :: Python :: 3
Classifier: Programming Language :: Python :: 3.10
Classifier: Programming Language :: Python :: 3.11
Requires-Dist: gevent (>=23.7.0,<24.0.0)
Requires-Dist: loguru (>=0.7.0,<0.8.0)
